pvporcupinedemo/LICENSE
pvporcupinedemo/porcupine_demo_file.py
pvporcupinedemo/porcupine_demo_mic.py
pvporcupinedemo-4.0.1.dist-info/METADATA
pvporcupinedemo-4.0.1.dist-info/WHEEL
pvporcupinedemo-4.0.1.dist-info/entry_points.txt
pvporcupinedemo-4.0.1.dist-info/top_level.txt
pvporcupinedemo-4.0.1.dist-info/RECORD
