Metadata-Version: 2.1
Name: pvporcupinedemo
Version: 4.0.1
Summary: Porcupine wake word engine demos
Home-page: https://github.com/Picovoice/porcupine
Author: Picovoice
Author-email: hello@picovoice.ai
Keywords: wake word engine,hotword detection,keyword spotting,wake word detection,voice commands
Classifier: Development Status :: 5 - Production/Stable
Classifier: Intended Audience :: Developers
Classifier: License :: OSI Approved :: Apache Software License
Classifier: Operating System :: OS Independent
Classifier: Programming Language :: Python :: 3
Classifier: Topic :: Multimedia :: Sound/Audio :: Speech
Requires-Python: >=3.9
Requires-Dist: pvporcupine==4.0.1
Requires-Dist: pvrecorder==1.2.4
